parabot/__init__.py
parabot/__main__.py
parabot/parabot.py
parabot/setup.py
parabot/utils.py
parabot-1.0.2.dist-info/LICENSE
parabot-1.0.2.dist-info/METADATA
parabot-1.0.2.dist-info/WHEEL
parabot-1.0.2.dist-info/top_level.txt
parabot-1.0.2.dist-info/RECORD
