Metadata-Version: 2.1
Name: parabot
Version: 1.0.2
Summary: Execute robotframework test files/tests in paralel, even without special preparation of them
Home-page: https://github.com/bednaJedna/parabot
Author: bednaJedna
Author-email: bednarik.radek@gmail.com
License: MIT
Keywords: robotframework,parallel execution,test,testing
Platform: UNKNOWN
Classifier: Programming Language :: Python :: 3
Classifier: License :: OSI Approved :: MIT License
Classifier: Operating System :: OS Independent
Requires-Python: >=3.8
Requires-Dist: robotframework
Requires-Dist: selenium
Requires-Dist: robotframework-seleniumLibrary
